{"version":1,"resource":"file:///home/vir0id/.themes/tealize/gtk-3.0/gtk-dark.css","entries":[{"id":"0Yhp.css","timestamp":1727281349516},{"id":"De8i.css","timestamp":1727281394437},{"id":"S1wE.css","source":"undoRedo.source","timestamp":1727281441576},{"id":"c3cm.css","timestamp":1727281469554},{"id":"Ixau.css","timestamp":1727281494316},{"id":"d7te.css","timestamp":1727281546381},{"id":"QBVD.css","timestamp":1727283180133},{"id":"cfky.css","timestamp":1727283406585},{"id":"qcut.css","timestamp":1727283436806},{"id":"5rzh.css","timestamp":1727283520509},{"id":"7W3w.css","timestamp":1727283769412},{"id":"VYp4.css","timestamp":1727284046433},{"id":"Tmey.css","source":"undoRedo.source","timestamp":1727284358044}]}