{"version":1,"resource":"file:///home/vir0id/%D0%97%D0%B0%D0%B3%D1%80%D1%83%D0%B7%D0%BA%D0%B8/repository/sources_test/PKGBUILD","entries":[{"id":"9HVj","timestamp":1702392618138},{"id":"GOYN","timestamp":1702393956018},{"id":"LdLv","timestamp":1702399126276},{"id":"o7LC","timestamp":1702399211285},{"id":"F8b6","timestamp":1702399921995},{"id":"G05x","timestamp":1702404150627},{"id":"P1DI","timestamp":1702482048518},{"id":"2ZOn","timestamp":1702482087780},{"id":"bY3M","timestamp":1702482151559},{"id":"BxKx","timestamp":1702520823918},{"id":"31Px","timestamp":1702521085109},{"id":"yqk1","timestamp":1702521102760},{"id":"9NGy","timestamp":1702521214205},{"id":"FsXv","timestamp":1702522456949},{"id":"MvzB","timestamp":1702522534991},{"id":"2APK","timestamp":1702568985342},{"id":"DWag","timestamp":1702569426531}]}